<?xml version="1.0" encoding="UTF-8"?><record_update table="catalog_ui_policy_action">
    <catalog_ui_policy_action action="INSERT_OR_UPDATE">
        <catalog_item display_value="New Hire Request">09f71b261b46e8108c5143f3cc4bcbb5</catalog_item>
        <catalog_variable>IO:0d81a4ae1b8ca450e7004229bc4bcb10</catalog_variable>
        <cleared>false</cleared>
        <disabled>ignore</disabled>
        <field/>
        <field_message/>
        <field_message_type>none</field_message_type>
        <mandatory>ignore</mandatory>
        <order>100</order>
        <sys_class_name>catalog_ui_policy_action</sys_class_name>
        <sys_created_by>bj.strohl</sys_created_by>
        <sys_created_on>2021-06-25 17:57:14</sys_created_on>
        <sys_id>d17cd1901b813890e7004229bc4bcb0a</sys_id>
        <sys_mod_count>0</sys_mod_count>
        <sys_name>leadership_program_type</sys_name>
        <sys_package display_value="New Hire" source="7314ba481ba581908c5143f3cc4bcbfe">7314ba481ba581908c5143f3cc4bcbfe</sys_package>
        <sys_policy/>
        <sys_scope display_value="New Hire">7314ba481ba581908c5143f3cc4bcbfe</sys_scope>
        <sys_update_name>catalog_ui_policy_action_d17cd1901b813890e7004229bc4bcb0a</sys_update_name>
        <sys_updated_by>Terry.Lillo</sys_updated_by>
        <sys_updated_on>2022-09-29 18:57:28</sys_updated_on>
        <table/>
        <ui_policy display_value="init (was : &quot;when prereq = yes:)">ab2531981b5f6c508c5143f3cc4bcbee</ui_policy>
        <value/>
        <value_action>ignore</value_action>
        <variable>leadership_program_type</variable>
        <variable_set/>
        <visible>ignore</visible>
    </catalog_ui_policy_action>
    <sys_claim action="INSERT_OR_UPDATE">
        <claim_owner_scope display_value="New Hire">7314ba481ba581908c5143f3cc4bcbfe</claim_owner_scope>
        <claim_timestamp>1816d58aacc0000001</claim_timestamp>
        <metadata_update_name>catalog_ui_policy_action_d17cd1901b813890e7004229bc4bcb0a</metadata_update_name>
        <previous_claim_app_version>1.0.1</previous_claim_app_version>
        <previous_claim_name>New Hire</previous_claim_name>
        <previous_claim_scope>7314ba481ba581908c5143f3cc4bcbfe</previous_claim_scope>
        <sys_created_by>Terry.Lillo</sys_created_by>
        <sys_created_on>2022-06-16 16:28:56</sys_created_on>
        <sys_id>dc4edab21b88d11062e50ed2cd4bcb77</sys_id>
        <sys_mod_count>0</sys_mod_count>
        <sys_updated_by>Terry.Lillo</sys_updated_by>
        <sys_updated_on>2022-09-29 18:57:28</sys_updated_on>
    </sys_claim>
</record_update>
